<?xml version="1.0" encoding="UTF-8"?>
<limit>
  <data-comment> </data-comment>
  <data-label>SIMPLE, 2011, Final analysis of Phase II, SD-proton</data-label>
  <data-reference>arXiv ref:1106.3014v1</data-reference>
  <data-values>{[5.050109043161 9.619415790947e-1;
        5.570498428683 4.223381796557e-1;
        6.092375022718 1.831283152881e-1;
        6.798359602472 9.494826123776e-2;
        7.629503570094 5.026272331288e-2;
        8.933253482140 2.468914634933e-2;
        10.64202753689 1.468314143814e-2;
        12.05013908001 1.052880890603e-2;
        13.68495145055 8.238628808168e-3;
        14.93900912616 7.152667670167e-3;
        17.11309891960 6.209850691310e-3;
        19.54764581163 5.302397503731e-3;
        22.07920311921 4.899681436329e-3;
        25.65550793164 4.508768212894e-3;
        29.39340618631 4.343186102984e-3;
        34.84152478923 4.218615673692e-3;
        41.41884113682 4.253838086382e-3;
        48.68491290419 4.434410793760e-3;
        59.20709919196 4.700162541171e-3;
        75.34993671456 5.258492862950e-3;
        97.26741431651 6.082101654195e-3;
        131.0246447370 7.456293840216e-3;
        163.9459148732 8.696137413031e-3;
        202.8261251636 1.014214400973e-2;
        243.2247807164 1.187787221646e-2;
        309.5828273570 1.468314143814e-2;
        383.0166355967 1.763034612304e-2;
        473.8718485965 2.125730440088e-2;
        622.2992611570 2.750736493213e-2;
        833.6000059702 3.574335243972e-2;
        1028.448120178 4.400176731773e-2;
        1283.338938831 5.507657734395e-2;
        2026.806244835 8.593203455221e-2]}</data-values>
  <date-of-announcement type="date">2011-06-15</date-of-announcement>
  <date-of-run-end type="date" nil="true"></date-of-run-end>
  <date-of-run-start type="date" nil="true"></date-of-run-start>
  <default-color>LtR</default-color>
  <default-style>Fill</default-style>
  <experiment>SIMPLE</experiment>
  <measurement-type>Dir</measurement-type>
  <nomhash type="yaml">--- 
choegoun: false
</nomhash>
  <public type="boolean">true</public>
  <result-type>Exp</result-type>
  <spin-dependency>SD</spin-dependency>
  <x-rescale>1</x-rescale>
  <x-units>GeV</x-units>
  <y-rescale>1e-36</y-rescale>
  <y-units>cm^2</y-units>
  <year type="integer">2011</year>
</limit>
